{
  "name": "cb_ts1",
  "data": [
    {
      "seriesName": "PRC_ELC_SPV",
      "seriesValues": [
        [
          2021,
          4.917012329642755
        ],
        [
          2023,
          0.0085545278619886
        ],
        [
          2026,
          0.0014662669095489
        ],
        [
          2027,
          0.0038632218591873003
        ],
        [
          2028,
          0.022145190938333302
        ],
        [
          2029,
          0.1149503355868607
        ],
        [
          2030,
          0.7789551275047162
        ],
        [
          2031,
          0.2398023919704543
        ],
        [
          2032,
          0.3153547913397959
        ],
        [
          2033,
          0.2482107190687689
        ],
        [
          2034,
          0.32352092591630527
        ],
        [
          2035,
          0.4432072304932755
        ],
        [
          2036,
          0.424437163717335
        ],
        [
          2037,
          0.6469315672373103
        ],
        [
          2038,
          0.6201470202896131
        ],
        [
          2039,
          0.9843363244189371
        ],
        [
          2040,
          0.782904912238535
        ],
        [
          2041,
          0.5575232329941676
        ],
        [
          2042,
          0.7779783455556736
        ],
        [
          2043,
          0.566635701898889
        ],
        [
          2044,
          0.514673795895909
        ],
        [
          2045,
          0.5097469951297046
        ],
        [
          2046,
          0.6688219513529708
        ],
        [
          2047,
          0.4539669861891677
        ],
        [
          2048,
          0.49722562529023606
        ],
        [
          2049,
          0.8761255295877657
        ],
        [
          2050,
          1.0113628370370933
        ]
      ]
    },
    {
      "seriesName": "PRC_ELC_WNO",
      "seriesValues": [
        [
          2021,
          2647.795235533041
        ],
        [
          2023,
          5.8950051015598
        ],
        [
          2024,
          27.09148356355545
        ],
        [
          2025,
          20.829408182436183
        ],
        [
          2026,
          20.306912771292247
        ],
        [
          2027,
          15.267496748526636
        ],
        [
          2028,
          13.54888893498381
        ],
        [
          2029,
          6.16995246892213
        ],
        [
          2030,
          6.03854467246915
        ]
      ]
    }
  ]
}