{
  "name": "base_ts1",
  "data": [
    {
      "seriesName": "PRC_ELC_COA",
      "seriesValues": [
        [
          2020,
          3993.92366634994
        ],
        [
          2021,
          3989.95672284994
        ],
        [
          2022,
          3985.33768984994
        ],
        [
          2023,
          3974.17968312194
        ],
        [
          2024,
          3949.57050350194
        ],
        [
          2025,
          3928.77077239194
        ],
        [
          2026,
          3898.56501531994
        ],
        [
          2027,
          3827.743224123
        ],
        [
          2028,
          3732.313343855937
        ],
        [
          2029,
          3631.0196814371866
        ],
        [
          2030,
          3521.331284500864
        ],
        [
          2031,
          3455.4891806514765
        ],
        [
          2032,
          3481.891822848329
        ],
        [
          2033,
          3372.0498351526576
        ],
        [
          2034,
          2948.1260396079574
        ],
        [
          2035,
          2189.119472847064
        ],
        [
          2036,
          1526.156355496798
        ],
        [
          2037,
          1054.6697932934328
        ],
        [
          2038,
          540.6818593634804
        ],
        [
          2039,
          336.67160422351265
        ],
        [
          2040,
          296.86692253
        ],
        [
          2041,
          280.82883253
        ],
        [
          2042,
          273.63940032457026
        ],
        [
          2043,
          270.07369253
        ],
        [
          2044,
          270.07369253
        ],
        [
          2045,
          270.07369253
        ],
        [
          2046,
          270.07369253
        ],
        [
          2047,
          263.49760253
        ],
        [
          2048,
          262.31485253
        ],
        [
          2049,
          226.23012777
        ],
        [
          2050,
          195.99320287
        ]
      ]
    },
    {
      "seriesName": "PRC_ELC_GAS",
      "seriesValues": [
        [
          2020,
          4588.826378559487
        ],
        [
          2021,
          5351.885556141898
        ],
        [
          2022,
          5017.402775839898
        ],
        [
          2023,
          5286.232404595262
        ],
        [
          2024,
          5383.7003734689
        ],
        [
          2025,
          5431.57925303638
        ],
        [
          2026,
          5499.651592297301
        ],
        [
          2027,
          5491.26843497974
        ],
        [
          2028,
          5305.42644085442
        ],
        [
          2029,
          5064.818972527438
        ],
        [
          2030,
          4653.016110683041
        ],
        [
          2031,
          4060.5915426699685
        ],
        [
          2032,
          3287.2073873814156
        ],
        [
          2033,
          2536.7085600713167
        ],
        [
          2034,
          2113.7885715897705
        ],
        [
          2035,
          1923.1650293730634
        ],
        [
          2036,
          1835.4095606760634
        ],
        [
          2037,
          1687.9278983971956
        ],
        [
          2038,
          1531.5858485125962
        ],
        [
          2039,
          1282.0800086575387
        ],
        [
          2040,
          1006.287574692195
        ],
        [
          2041,
          807.7024910313
        ],
        [
          2042,
          757.580000837434
        ],
        [
          2043,
          668.1823630108788
        ],
        [
          2044,
          625.7970123762545
        ],
        [
          2045,
          589.3692297611977
        ],
        [
          2046,
          539.6537793938734
        ],
        [
          2047,
          528.695605760377
        ],
        [
          2048,
          514.5800861104055
        ],
        [
          2049,
          497.8145557151131
        ],
        [
          2050,
          466.04802636195825
        ]
      ]
    },
    {
      "seriesName": "PRC_ELC_GEO",
      "seriesValues": [
        [
          2020,
          53.834430634
        ],
        [
          2021,
          54.300907234
        ],
        [
          2022,
          54.986902234
        ],
        [
          2023,
          54.986902234
        ],
        [
          2024,
          54.986902234
        ],
        [
          2025,
          54.986902234
        ],
        [
          2026,
          54.986902234
        ],
        [
          2027,
          54.986902234
        ],
        [
          2028,
          54.986902234
        ],
        [
          2029,
          54.986902234
        ],
        [
          2030,
          54.986902234
        ],
        [
          2031,
          54.986902234
        ],
        [
          2032,
          54.986902234
        ],
        [
          2033,
          54.986902234
        ],
        [
          2034,
          54.986902234
        ],
        [
          2035,
          54.986902234
        ],
        [
          2036,
          52.735892434
        ],
        [
          2037,
          50.682007634
        ],
        [
          2038,
          50.682007634
        ],
        [
          2039,
          50.682007634
        ],
        [
          2040,
          48.901890034
        ],
        [
          2041,
          48.901890034
        ],
        [
          2042,
          48.901890034
        ],
        [
          2043,
          48.901890034
        ],
        [
          2044,
          47.618275114
        ],
        [
          2045,
          44.411287914
        ],
        [
          2046,
          44.411287914
        ],
        [
          2047,
          42.629908714
        ],
        [
          2048,
          38.283507474000004
        ],
        [
          2049,
          35.96198685
        ],
        [
          2050,
          30.969548636
        ]
      ]
    },
    {
      "seriesName": "PRC_ELC_HYD",
      "seriesValues": [
        [
          2020,
          695.02434109264
        ],
        [
          2021,
          676.50809652064
        ],
        [
          2022,
          656.10365938464
        ],
        [
          2023,
          611.93447881864
        ],
        [
          2024,
          582.80071903664
        ],
        [
          2025,
          559.23236572464
        ],
        [
          2026,
          491.41423453064
        ],
        [
          2027,
          455.33655580664
        ],
        [
          2028,
          434.52024411864
        ],
        [
          2029,
          412.89259747064
        ],
        [
          2030,
          396.74749855864
        ],
        [
          2031,
          379.47227413664
        ],
        [
          2032,
          343.90366047464
        ],
        [
          2033,
          316.17638599064
        ],
        [
          2034,
          290.18021910064
        ],
        [
          2035,
          277.36262803664
        ],
        [
          2036,
          264.91682418464
        ],
        [
          2037,
          263.56839141064
        ],
        [
          2038,
          247.36539767464
        ],
        [
          2039,
          238.39601778064
        ],
        [
          2040,
          216.37863135263999
        ],
        [
          2041,
          196.84087872263999
        ],
        [
          2042,
          189.54830085064
        ],
        [
          2043,
          161.07493505064
        ],
        [
          2044,
          136.55850510864
        ],
        [
          2045,
          123.90876361664
        ],
        [
          2046,
          119.99294961064
        ],
        [
          2047,
          111.78739282064
        ],
        [
          2048,
          105.22473084948
        ],
        [
          2049,
          98.66265091748
        ],
        [
          2050,
          84.88373374258
        ]
      ]
    },
    {
      "seriesName": "PRC_ELC_MSW",
      "seriesValues": [
        [
          2020,
          57.396999212781864
        ],
        [
          2021,
          57.26296482175703
        ],
        [
          2022,
          57.207578465278885
        ],
        [
          2023,
          57.207578465278885
        ],
        [
          2024,
          106.56048101500151
        ],
        [
          2025,
          106.56048101500153
        ],
        [
          2026,
          106.65429331906027
        ],
        [
          2027,
          106.65429331906027
        ],
        [
          2028,
          106.65429331906027
        ],
        [
          2029,
          106.65429331906027
        ],
        [
          2030,
          106.65429331906027
        ],
        [
          2031,
          106.65429331906027
        ],
        [
          2032,
          106.65046078385434
        ],
        [
          2033,
          106.64663434170916
        ],
        [
          2034,
          106.62027311636487
        ],
        [
          2035,
          106.61872245605049
        ],
        [
          2036,
          106.61872245605049
        ],
        [
          2037,
          106.61872245605049
        ],
        [
          2038,
          106.61872245605049
        ],
        [
          2039,
          106.61872245605049
        ],
        [
          2040,
          106.61872245605049
        ],
        [
          2041,
          106.61872245605049
        ],
        [
          2042,
          106.61872245605049
        ],
        [
          2043,
          106.61872245605049
        ],
        [
          2044,
          106.61872245605049
        ],
        [
          2045,
          108.86133422810731
        ],
        [
          2046,
          111.0922425416898
        ],
        [
          2047,
          111.0922425416898
        ],
        [
          2048,
          112.48779904036829
        ],
        [
          2049,
          115.63887131476754
        ],
        [
          2050,
          118.54627375927362
        ]
      ]
    },
    {
      "seriesName": "PRC_ELC_NUC",
      "seriesValues": [
        [
          2020,
          2832.84083807436
        ],
        [
          2021,
          2832.84083807436
        ],
        [
          2022,
          2931.07984491036
        ],
        [
          2023,
          2931.07984491036
        ],
        [
          2024,
          2931.07984491036
        ],
        [
          2025,
          2931.07984491036
        ],
        [
          2026,
          2931.07984491036
        ],
        [
          2027,
          2931.07984491036
        ],
        [
          2028,
          2931.07984491036
        ],
        [
          2029,
          2931.07984491036
        ],
        [
          2030,
          2931.07984491036
        ],
        [
          2031,
          2931.07984491036
        ],
        [
          2032,
          2931.07984491036
        ],
        [
          2033,
          2931.07984491036
        ],
        [
          2034,
          2912.60935857036
        ],
        [
          2035,
          2850.19253122636
        ],
        [
          2036,
          2803.76341188636
        ],
        [
          2037,
          2658.70789250636
        ],
        [
          2038,
          2554.93116816636
        ],
        [
          2039,
          2313.30125691636
        ],
        [
          2040,
          2129.65008183636
        ],
        [
          2041,
          2022.18020642836
        ],
        [
          2042,
          1853.13010848436
        ],
        [
          2043,
          1793.20032368436
        ],
        [
          2044,
          1767.18859180436
        ],
        [
          2045,
          1714.78907662436
        ],
        [
          2046,
          1591.05442062036
        ],
        [
          2047,
          1558.14167681436
        ],
        [
          2048,
          1493.46086578598
        ],
        [
          2049,
          1296.58945369398
        ],
        [
          2050,
          1063.37247968576
        ]
      ]
    },
    {
      "seriesName": "PRC_ELC_SPV",
      "seriesValues": [
        [
          2020,
          325.6232775345437
        ],
        [
          2021,
          414.2056318033139
        ],
        [
          2022,
          514.1617584046777
        ],
        [
          2023,
          586.4004065047607
        ],
        [
          2024,
          656.8880857137825
        ],
        [
          2025,
          738.7554131006772
        ],
        [
          2026,
          861.8839244215392
        ],
        [
          2027,
          1129.443913881872
        ],
        [
          2028,
          1516.2547674876087
        ],
        [
          2029,
          2019.4743272528956
        ],
        [
          2030,
          2660.473683365968
        ],
        [
          2031,
          3386.5432886567332
        ],
        [
          2032,
          4262.030149232243
        ],
        [
          2033,
          5243.891426899139
        ],
        [
          2034,
          6251.452303969275
        ],
        [
          2035,
          7386.7097559562435
        ],
        [
          2036,
          8311.435076894059
        ],
        [
          2037,
          9202.747795029542
        ],
        [
          2038,
          10171.200138310867
        ],
        [
          2039,
          11052.425840655445
        ],
        [
          2040,
          11679.086491421864
        ],
        [
          2041,
          12152.336314888827
        ],
        [
          2042,
          12522.868781649768
        ],
        [
          2043,
          12846.939993539248
        ],
        [
          2044,
          13115.458097010856
        ],
        [
          2045,
          13429.912684063971
        ],
        [
          2046,
          13759.898993127228
        ],
        [
          2047,
          13976.34539845322
        ],
        [
          2048,
          14207.753998318434
        ],
        [
          2049,
          14625.29140388796
        ],
        [
          2050,
          15131.029652526404
        ]
      ]
    },
    {
      "seriesName": "PRC_ELC_STH",
      "seriesValues": [
        [
          2020,
          12.675812456
        ],
        [
          2021,
          12.675812456
        ],
        [
          2022,
          12.675812456
        ],
        [
          2023,
          12.675812456
        ],
        [
          2024,
          12.675812456
        ],
        [
          2025,
          12.675812456
        ],
        [
          2026,
          12.675812456
        ],
        [
          2027,
          12.675812456
        ],
        [
          2028,
          12.675812456
        ],
        [
          2029,
          12.675812456
        ],
        [
          2030,
          12.675812456
        ],
        [
          2031,
          12.675812456
        ],
        [
          2032,
          12.675812456
        ],
        [
          2033,
          12.675812456
        ],
        [
          2034,
          12.675812456
        ],
        [
          2035,
          12.675812456
        ],
        [
          2036,
          12.675812456
        ],
        [
          2037,
          12.675812456
        ],
        [
          2038,
          12.675812456
        ],
        [
          2039,
          12.675812456
        ],
        [
          2040,
          12.675812456
        ],
        [
          2041,
          12.675812456
        ],
        [
          2042,
          12.675812456
        ],
        [
          2043,
          12.675812456
        ],
        [
          2044,
          12.675812456
        ],
        [
          2045,
          12.675812456
        ],
        [
          2046,
          12.675812456
        ],
        [
          2047,
          12.675812456
        ],
        [
          2048,
          12.675812456
        ],
        [
          2049,
          12.675812456
        ],
        [
          2050,
          12.675812456
        ]
      ]
    },
    {
      "seriesName": "PRC_ELC_WNF",
      "seriesValues": [
        [
          2020,
          0.410310168
        ],
        [
          2021,
          0.48600616799999996
        ],
        [
          2022,
          0.48600616799999996
        ],
        [
          2023,
          0.48600616799999996
        ],
        [
          2024,
          0.48600616799999996
        ],
        [
          2025,
          0.48600616799999996
        ],
        [
          2026,
          0.48600616799999996
        ],
        [
          2027,
          0.48600616799999996
        ],
        [
          2028,
          0.48600616799999996
        ],
        [
          2029,
          0.48600616799999996
        ],
        [
          2030,
          0.48600616799999996
        ],
        [
          2031,
          0.48600616799999996
        ],
        [
          2032,
          0.48600616799999996
        ],
        [
          2033,
          0.48600616799999996
        ],
        [
          2034,
          0.48600616799999996
        ],
        [
          2035,
          0.48600616799999996
        ],
        [
          2036,
          0.48600616799999996
        ],
        [
          2037,
          0.48600616799999996
        ],
        [
          2038,
          0.48600616799999996
        ],
        [
          2039,
          0.48600616799999996
        ],
        [
          2040,
          0.48600616799999996
        ],
        [
          2041,
          0.48600616799999996
        ],
        [
          2042,
          0.48600616799999996
        ],
        [
          2043,
          0.48600616799999996
        ],
        [
          2044,
          0.48600616799999996
        ],
        [
          2045,
          0.48600616799999996
        ],
        [
          2046,
          0.48600616799999996
        ],
        [
          2047,
          0.48600616799999996
        ],
        [
          2048,
          0.48600616799999996
        ],
        [
          2049,
          0.48600616799999996
        ],
        [
          2050,
          0.48600616799999996
        ]
      ]
    },
    {
      "seriesName": "PRC_ELC_WNO",
      "seriesValues": [
        [
          2020,
          1312.365629636
        ],
        [
          2021,
          1494.591455344
        ],
        [
          2022,
          1558.361395998
        ],
        [
          2023,
          1589.76239291
        ],
        [
          2024,
          1600.6260152711684
        ],
        [
          2025,
          1620.5844893683231
        ],
        [
          2026,
          1638.7424271352447
        ],
        [
          2027,
          1638.993534029303
        ],
        [
          2028,
          1644.7740395298044
        ],
        [
          2029,
          1650.5722969854778
        ],
        [
          2030,
          1660.2480994432467
        ],
        [
          2031,
          1667.305138817296
        ],
        [
          2032,
          1675.1440272653504
        ],
        [
          2033,
          1683.85119777682
        ],
        [
          2034,
          1693.52263822499
        ],
        [
          2035,
          1704.2649476023007
        ],
        [
          2036,
          1704.3036682097281
        ],
        [
          2037,
          1704.3423888171558
        ],
        [
          2038,
          1704.3811094245834
        ],
        [
          2039,
          1704.419830032011
        ],
        [
          2040,
          1704.3908973394384
        ],
        [
          2041,
          1704.429617946866
        ],
        [
          2042,
          1704.4683385542937
        ],
        [
          2043,
          1704.5070591617214
        ],
        [
          2044,
          1704.545779769149
        ],
        [
          2045,
          1704.5845003765764
        ],
        [
          2046,
          1704.553378808004
        ],
        [
          2047,
          1704.4515035574316
        ],
        [
          2048,
          1704.6287881645574
        ],
        [
          2049,
          1703.813824580078
        ],
        [
          2050,
          1703.5720721095986
        ]
      ]
    },
    {
      "seriesName": "PRC_ELC_BSL",
      "seriesValues": [
        [
          2021,
          0.2225147
        ]
      ]
    }
  ]
}